MANIFEST.in
setup.cfg
setup.py
py.saunter.egg-info/PKG-INFO
py.saunter.egg-info/SOURCES.txt
py.saunter.egg-info/dependency_links.txt
py.saunter.egg-info/entry_points.txt
py.saunter.egg-info/requires.txt
py.saunter.egg-info/top_level.txt
saunter/ConfigWrapper.py
saunter/SaunterSelenium.py
saunter/SaunterWebDriver.py
saunter/SeleniumWrapper.py
saunter/__init__.py
saunter/exceptions.py
saunter/main.py
saunter/matchers.py
saunter/saucelabs.py
saunter/web_element.py
saunter/_defaults/conftest.py
saunter/_defaults/pytest.ini
saunter/_defaults/conf/saunter.ini.default
saunter/_defaults/tailored/page.py
saunter/_defaults/tailored/remotecontrol.py
saunter/_defaults/tailored/webdriver.py
saunter/generators/__init__.py
saunter/generators/string_data.py
saunter/po/__init__.py
saunter/po/remotecontrol/__init__.py
saunter/po/remotecontrol/checkbox.py
saunter/po/remotecontrol/element.py
saunter/po/remotecontrol/number.py
saunter/po/remotecontrol/page.py
saunter/po/remotecontrol/select.py
saunter/po/remotecontrol/text.py
saunter/po/webdriver/__init__.py
saunter/po/webdriver/attribute.py
saunter/po/webdriver/checkbox.py
saunter/po/webdriver/element.py
saunter/po/webdriver/multi_select.py
saunter/po/webdriver/number.py
saunter/po/webdriver/page.py
saunter/po/webdriver/select.py
saunter/po/webdriver/text.py
saunter/po/webdriver/unicode.py
saunter/providers/__init__.py
saunter/providers/csv_provider.py
saunter/providers/django_provider.py
saunter/providers/sqlite3_provider.py
saunter/testcase/__init__.py
saunter/testcase/base.py
saunter/testcase/remotecontrol.py
saunter/testcase/webdriver.py