Metadata-Version: 1.0
Name: py.saunter
Version: 0.62
Summary: An opinionated Selenium framework
Home-page: https://github.com/Element-34/py.saunter
Author: adam goucher
Author-email: adam@element34.ca
License: LICENSE.txt
Platform: UNKNOWN
Classifier: Development Status :: 4 - Beta
Classifier: Intended Audience :: Developers
Classifier: License :: OSI Approved :: Apache Software License
Classifier: Operating System :: POSIX
Classifier: Operating System :: Microsoft :: Windows
Classifier: Operating System :: MacOS :: MacOS X
Classifier: Topic :: Software Development :: Testing
Classifier: Topic :: Software Development :: Quality Assurance
Classifier: Programming Language :: Python
